tuberiassantiagoa/__init__.py
tuberiassantiagoa/matematicas.py
tuberiassantiagoa/tuberias.py
tuberiassantiagoa-0.1.1.dist-info/METADATA
tuberiassantiagoa-0.1.1.dist-info/WHEEL
tuberiassantiagoa-0.1.1.dist-info/RECORD
