Metadata-Version: 2.1
Name: tuberiassantiagoa
Version: 0.1.1
Summary: Ejemplo de paquete
Author: Santiago Quiñones
Author-email: lsquinones@gmail.com
Requires-Python: >=3.10.0,<3.12
Classifier: Programming Language :: Python :: 3
Classifier: Programming Language :: Python :: 3.10
Classifier: Programming Language :: Python :: 3.11
